mcp_excel/__init__.py
mcp_excel/auth.py
mcp_excel/loader.py
mcp_excel/logging.py
mcp_excel/naming.py
mcp_excel/naming_improved.py
mcp_excel/server.py
mcp_excel/types.py
mcp_excel/watcher.py
mcp_excel/formats/__init__.py
mcp_excel/formats/detector.py
mcp_excel/formats/handlers.py
mcp_excel/formats/manager.py
mcp_excel/formats/normalizer.py
mcp_server_excel_sql-0.4.1.dist-info/licenses/LICENSE
mcp_server_excel_sql-0.4.1.dist-info/METADATA
mcp_server_excel_sql-0.4.1.dist-info/WHEEL
mcp_server_excel_sql-0.4.1.dist-info/entry_points.txt
mcp_server_excel_sql-0.4.1.dist-info/top_level.txt
mcp_server_excel_sql-0.4.1.dist-info/RECORD
