Metadata-Version: 2.4
Name: mcp-server-excel-sql
Version: 0.4.1
Summary: Let Claude query Excel files using SQL - no SQL knowledge required
Author-email: Ivan <ivan@eriad.com>
License-Expression: MIT
Project-URL: Homepage, https://github.com/ivan-loh/mcp-excel
Project-URL: Repository, https://github.com/ivan-loh/mcp-excel
Project-URL: Issues, https://github.com/ivan-loh/mcp-excel/issues
Keywords: excel,sql,spreadsheet,query,duckdb,mcp,model-context-protocol,claude,llm,ai,analytics,data-analysis,business-intelligence,etl,data
Classifier: Development Status :: 4 - Beta
Classifier: Environment :: Console
Classifier: Intended Audience :: Developers
Classifier: Intended Audience :: End Users/Desktop
Classifier: Intended Audience :: Financial and Insurance Industry
Classifier: Intended Audience :: Science/Research
Classifier: Natural Language :: English
Classifier: Operating System :: OS Independent
Classifier: Programming Language :: Python :: 3
Classifier: Programming Language :: Python :: 3.11
Classifier: Programming Language :: Python :: 3.12
Classifier: Programming Language :: Python :: 3.13
Classifier: Topic :: Database
Classifier: Topic :: Database :: Front-Ends
Classifier: Topic :: Office/Business
Classifier: Topic :: Office/Business :: Financial :: Spreadsheet
Classifier: Topic :: Scientific/Engineering :: Information Analysis
Requires-Python: >=3.11
License-File: LICENSE
Requires-Dist: fastmcp>=2.12.5
Requires-Dist: duckdb>=1.0.0
Requires-Dist: pyyaml>=6.0
Requires-Dist: click>=8.1
Requires-Dist: pandas>=2.1
Requires-Dist: openpyxl>=3.1
Requires-Dist: watchdog>=3.0
Provides-Extra: dev
Requires-Dist: pytest>=7.4; extra == "dev"
Requires-Dist: pytest-cov>=4.1; extra == "dev"
Requires-Dist: pytest-asyncio>=0.23; extra == "dev"
Dynamic: license-file
